LICENSE
MANIFEST.in
README.md
setup.py
geometa/__init__.py
geometa/constants.py
geometa/exceptions.py
geometa/rest.py
geometa/utils.py
geometa/schema/__init__.py
geometa/schema/base.py
geometa/schema/opensearchgeo.py
girder_geospatial.egg-info/PKG-INFO
girder_geospatial.egg-info/SOURCES.txt
girder_geospatial.egg-info/dependency_links.txt
girder_geospatial.egg-info/entry_points.txt
girder_geospatial.egg-info/requires.txt
girder_geospatial.egg-info/top_level.txt