Metadata-Version: 2.1
Name: girder-geospatial
Version: 0.2.0
Summary: Generate metadata for various geospatial datasets
Home-page: https://github.com/OpenGeoscience/girder_geospatial
Maintainer: Kitware, Inc.
Maintainer-email: kitware@kitware.com
License: UNKNOWN
Platform: UNKNOWN
